gh_safeapprove/__init__.py
gh_safeapprove/approver.py
gh_safeapprove/cli.py
gh_safeapprove/github_client.py
gh_safeapprove/utils.py
gh_safeapprove-0.1.0.dist-info/METADATA
gh_safeapprove-0.1.0.dist-info/WHEEL
gh_safeapprove-0.1.0.dist-info/entry_points.txt
gh_safeapprove-0.1.0.dist-info/licenses/LICENSE
gh_safeapprove-0.1.0.dist-info/RECORD
