Metadata-Version: 2.4
Name: gh-safeapprove
Version: 0.1.0
Summary: A GitHub CLI-compatible Python tool to safely auto-approve pull requests based on customizable rules
Author-email: Daniel Meint <pilots-4-trilogy@icloud.com>
License: MIT
License-File: LICENSE
Keywords: approval,automation,cli,github,pull-request
Classifier: Development Status :: 4 - Beta
Classifier: Intended Audience :: Developers
Classifier: License :: OSI Approved :: MIT License
Classifier: Programming Language :: Python :: 3
Classifier: Programming Language :: Python :: 3.8
Classifier: Programming Language :: Python :: 3.9
Classifier: Programming Language :: Python :: 3.10
Classifier: Programming Language :: Python :: 3.11
Classifier: Topic :: Software Development :: Libraries :: Python Modules
Classifier: Topic :: Software Development :: Version Control :: Git
Requires-Python: >=3.8
Requires-Dist: click>=8.0.0
Requires-Dist: hatchling>=1.27.0
Requires-Dist: pytest>=8.3.5
Requires-Dist: typer>=0.9.0
Provides-Extra: dev
Requires-Dist: black>=23.0.0; extra == 'dev'
Requires-Dist: mypy>=1.0.0; extra == 'dev'
Requires-Dist: pytest>=7.0.0; extra == 'dev'
Requires-Dist: ruff>=0.1.0; extra == 'dev'
